odoo/addons/auth_totp_ip_check/LICENSE
odoo/addons/auth_totp_ip_check/README.rst
odoo/addons/auth_totp_ip_check/__init__.py
odoo/addons/auth_totp_ip_check/__manifest__.py
odoo/addons/auth_totp_ip_check/images/screen.png
odoo/addons/auth_totp_ip_check/models/__init__.py
odoo/addons/auth_totp_ip_check/models/allowed_cidrs.py
odoo/addons/auth_totp_ip_check/models/res_users.py
odoo/addons/auth_totp_ip_check/security/ir.model.access.csv
odoo/addons/auth_totp_ip_check/static/description/icon.png
odoo/addons/auth_totp_ip_check/static/description/index.html
odoo/addons/auth_totp_ip_check/tests/TEST_INSTRUCTIONS.rst
odoo/addons/auth_totp_ip_check/views/auth_totp_cidr.xml
odoo_addon_auth_totp_ip_check-18.0.1.0.0.8.dist-info/METADATA
odoo_addon_auth_totp_ip_check-18.0.1.0.0.8.dist-info/WHEEL
odoo_addon_auth_totp_ip_check-18.0.1.0.0.8.dist-info/top_level.txt
odoo_addon_auth_totp_ip_check-18.0.1.0.0.8.dist-info/RECORD
